xeda/__init__.py
xeda/board.py
xeda/cli.py
xeda/cli_utils.py
xeda/cocotb.py
xeda/console.py
xeda/dataclass.py
xeda/design.py
xeda/gtkwave.py
xeda/proc_utils.py
xeda/tool.py
xeda/types.py
xeda/units.py
xeda/utils.py
xeda/version.py
xeda/xedaproject.py
xeda/data/__init__.py
xeda/data/boards.toml
xeda/data/boards/__init__.py
xeda/data/boards/ulx3s/__init__.py
xeda/data/boards/ulx3s/board.lpf
xeda/flow/__init__.py
xeda/flow/flow.py
xeda/flow/fpga.py
xeda/flow/sim.py
xeda/flow/synth.py
xeda/flow_runner/__init__.py
xeda/flow_runner/default_runner.py
xeda/flow_runner/remote.py
xeda/flow_runner/dse/__init__.py
xeda/flow_runner/dse/dse_runner.py
xeda/flow_runner/dse/fmax.py
xeda/flows/__init__.py
xeda/flows/nextpnr.py
xeda/flows/openfpgaloader.py
xeda/flows/vcs.py
xeda/flows/bsc/__init__.py
xeda/flows/bsc/templates/bluetcl_typeinfo.tcl
xeda/flows/dc/__init__.py
xeda/flows/dc/templates/constraints.sdc
xeda/flows/dc/templates/dc_script.tcl
xeda/flows/dc/templates/run_old.tcl
xeda/flows/diamond/__init__.py
xeda/flows/diamond/templates/__init__.py
xeda/flows/diamond/templates/constraints.fdc
xeda/flows/diamond/templates/constraints.ldc
xeda/flows/diamond/templates/constraints.sdc
xeda/flows/diamond/templates/synth.tcl
xeda/flows/ghdl/__init__.py
xeda/flows/ise/__init__.py
xeda/flows/ise/templates/constraints.ucf
xeda/flows/ise/templates/constraints.xcf
xeda/flows/ise/templates/ise_synth.tcl
xeda/flows/modelsim/__init__.py
xeda/flows/modelsim/templates/__init__.py
xeda/flows/modelsim/templates/run.tcl
xeda/flows/nvc/__init__.py
xeda/flows/openroad/__init__.py
xeda/flows/openroad/openroad_scripts/LICENSE.md
xeda/flows/openroad/openroad_scripts/README.md
xeda/flows/openroad/openroad_scripts/deleteNonClkNets.tcl
xeda/flows/openroad/openroad_scripts/deletePowerNets.tcl
xeda/flows/openroad/openroad_scripts/gui.tcl
xeda/flows/openroad/openroad_scripts/view_cells.tcl
xeda/flows/openroad/openroad_scripts/utils/def2stream.py
xeda/flows/openroad/templates/clocks.sdc
xeda-0.2.10.dist-info/licenses/LICENSE.txt
xeda-0.2.10.dist-info/METADATA
xeda-0.2.10.dist-info/WHEEL
xeda-0.2.10.dist-info/entry_points.txt
xeda-0.2.10.dist-info/top_level.txt
xeda-0.2.10.dist-info/RECORD
