Metadata-Version: 2.4
Name: xeda
Version: 0.2.10
Summary: Cross EDA Abstraction and Automation
Author-email: Kamyar Mohajerani <kammoh@gmail.com>
License: 
Project-URL: homepage, https://github.com/XedaHQ/xeda
Project-URL: repository, https://github.com/XedaHQ/xeda.git
Project-URL: changelog, https://github.com/XedaHQ/xeda/blob/dev/CHANGELOG.md
Keywords: EDA,Electronic,Design,Automation,Tool,Synthesis,Simulation,Simulator,Verification,Hardware,Verilog,VHDL,FPGA,ASIC
Classifier: Programming Language :: Python :: 3.9
Classifier: Programming Language :: Python :: 3.10
Classifier: Programming Language :: Python :: 3.11
Classifier: Programming Language :: Python :: 3.12
Classifier: Programming Language :: Python :: 3.13
Classifier: Development Status :: 5 - Production/Stable
Classifier: License :: OSI Approved :: Apache Software License
Classifier: Intended Audience :: Science/Research
Classifier: Topic :: Scientific/Engineering :: Electronic Design Automation (EDA)
Classifier: Topic :: Utilities
Requires-Python: >=3.9
License-File: LICENSE.txt
Requires-Dist: jinja2~=3.1
Requires-Dist: pydantic<2.0,>=1.10
Requires-Dist: tomli~=2.0; python_version < "3.11"
Requires-Dist: python-box~=7.2
Requires-Dist: attrs<26.0,>=25
Requires-Dist: cattrs<26.0,>=24.1
Requires-Dist: attrs_strict~=1.0
Requires-Dist: pathvalidate<4.0,>=3.0
Requires-Dist: click~=8.1
Requires-Dist: click_help_colors~=0.9
Requires-Dist: coloredlogs~=15.0
Requires-Dist: rich<14.0,>=13.0
Requires-Dist: pebble~=5.0
Requires-Dist: pint~=0.24
Requires-Dist: importlib_resources>=6.0
Requires-Dist: simpleeval~=1.0
Requires-Dist: PyYAML~=6.0
Requires-Dist: varname<0.15,>=0.13.3
Requires-Dist: overrides~=7.7
Requires-Dist: simple_term_menu~=1.6
Requires-Dist: psutil~=7.0
Requires-Dist: pyvcd~=0.4
Requires-Dist: GitPython~=3.1
Requires-Dist: fabric~=3.2
Requires-Dist: execnet~=2.1
Requires-Dist: devtools~=0.12
Requires-Dist: colorama~=0.4
Provides-Extra: docs
Requires-Dist: sphinx; extra == "docs"
Requires-Dist: sphinx-tabs; extra == "docs"
Requires-Dist: sphinx-jinja; extra == "docs"
Requires-Dist: autodoc_pydantic; extra == "docs"
Provides-Extra: dev
Requires-Dist: pytest; extra == "dev"
Requires-Dist: mypy; extra == "dev"
Requires-Dist: black; extra == "dev"
Requires-Dist: flakeheaven; extra == "dev"
Requires-Dist: tox; extra == "dev"
Dynamic: license-file
